pyoctaveband/__init__.py
pyoctaveband/calibration.py
pyoctaveband/core.py
pyoctaveband/filter_design.py
pyoctaveband/frequencies.py
pyoctaveband/parametric_filters.py
pyoctaveband/utils.py
pyoctaveband-1.1.3.dist-info/licenses/LICENSE
pyoctaveband-1.1.3.dist-info/METADATA
pyoctaveband-1.1.3.dist-info/WHEEL
pyoctaveband-1.1.3.dist-info/top_level.txt
pyoctaveband-1.1.3.dist-info/RECORD
