Metadata-Version: 2.4
Name: PyOctaveBand
Version: 1.1.3
Summary: Octave-Band and Fractional Octave-Band filter for signals in time domain.
Author-email: Jose Manuel Requena Plens <jmrplens@gmail.com>
Project-URL: Homepage, https://github.com/jmrplens/PyOctaveBand
Project-URL: Bug Tracker, https://github.com/jmrplens/PyOctaveBand/issues
Classifier: Programming Language :: Python :: 3
Classifier: License :: OSI Approved :: MIT License
Classifier: Operating System :: OS Independent
Requires-Python: >=3.11
License-File: LICENSE
Requires-Dist: numpy
Requires-Dist: scipy
Requires-Dist: matplotlib
Requires-Dist: numba
Dynamic: license-file
